{"total":245,"pageSize":10,"pageCount":25,"data":[{"title":"立秋随想","slug":"立秋随想","date":"2018-08-07T06:48:00.000Z","updated":"2021-06-15T03:45:27.165Z","comments":true,"path":"api/articles/立秋随想.json","excerpt":null,"keywords":null,"cover":"https://ww1.sinaimg.cn/large/8bf740e1gw1f6ntgpawajj20z60n9tbf.jpg","content":null,"raw":null,"categories":[{"name":"悟","path":"api/categories/悟.json"}],"tags":[{"name":"二十四节气","path":"api/tags/二十四节气.json"},{"name":"立秋","path":"api/tags/立秋.json"}]},{"title":"分享：中医归正 --- 告诉你数字背后的故事","slug":"分享：中医归正-告诉你数字背后的故事","date":"2018-07-30T00:00:00.000Z","updated":"2021-06-15T03:45:27.157Z","comments":true,"path":"api/articles/分享：中医归正-告诉你数字背后的故事.json","excerpt":null,"keywords":null,"cover":"http://wx4.sinaimg.cn/large/8bf740e1gy1ftrl4bgo5jj20c308v3yu.jpg","content":null,"raw":null,"categories":[{"name":"摘","path":"api/categories/摘.json"}],"tags":[{"name":"阴阳","path":"api/tags/阴阳.json"},{"name":"六节","path":"api/tags/六节.json"},{"name":"中医归正","path":"api/tags/中医归正.json"}]},{"title":"分享：中医归正 - 你所知道的中医都错了","slug":"分享：中医归正-你所知道的中医都错了","date":"2018-07-29T03:00:00.000Z","updated":"2021-06-15T03:45:27.153Z","comments":true,"path":"api/articles/分享：中医归正-你所知道的中医都错了.json","excerpt":null,"keywords":null,"cover":"http://wx3.sinaimg.cn/large/8bf740e1gy1ftrk3xkc4pj20p00b7qn9.jpg","content":null,"raw":null,"categories":[{"name":"摘","path":"api/categories/摘.json"}],"tags":[{"name":"阴阳","path":"api/tags/阴阳.json"},{"name":"六节","path":"api/tags/六节.json"},{"name":"中医归正","path":"api/tags/中医归正.json"}]},{"title":"分享：中医归正 - 关于三伏炙---你不知道的也许太多","slug":"分享：中医归正-关于三伏炙你不知道的也许太多","date":"2018-07-28T00:00:00.000Z","updated":"2021-06-15T03:45:27.153Z","comments":true,"path":"api/articles/分享：中医归正-关于三伏炙你不知道的也许太多.json","excerpt":null,"keywords":null,"cover":"http://wx1.sinaimg.cn/mw690/8bf740e1gy1fhx2uo3bntj20hs0bc0tn.jpg","content":null,"raw":null,"categories":[{"name":"摘","path":"api/categories/摘.json"}],"tags":[{"name":"阴阳","path":"api/tags/阴阳.json"},{"name":"六节","path":"api/tags/六节.json"},{"name":"中医归正","path":"api/tags/中医归正.json"},{"name":"三伏养生","path":"api/tags/三伏养生.json"}]},{"title":"分享：归正先生-关于审美","slug":"分享：中医归正-关于审美","date":"2018-07-02T11:08:00.000Z","updated":"2021-06-15T03:45:27.153Z","comments":true,"path":"api/articles/分享：中医归正-关于审美.json","excerpt":null,"keywords":null,"cover":"http://wx4.sinaimg.cn/large/8bf740e1gy1fsvq5pbs6wj20ku0dxh48.jpg","content":null,"raw":null,"categories":[{"name":"摘","path":"api/categories/摘.json"}],"tags":[{"name":"归正先生","path":"api/tags/归正先生.json"},{"name":"审美","path":"api/tags/审美.json"}]},{"title":"分享：归正先生-生气通天谈脏象","slug":"分享：中医归正-生气通天谈脏象","date":"2018-06-27T02:48:00.000Z","updated":"2021-06-15T03:45:27.157Z","comments":true,"path":"api/articles/分享：中医归正-生气通天谈脏象.json","excerpt":null,"keywords":null,"cover":"http://wx1.sinaimg.cn/large/8bf740e1gy1fsmhi31nvfj20p00s01kx.jpg","content":null,"raw":null,"categories":[{"name":"摘","path":"api/categories/摘.json"}],"tags":[{"name":"归正先生","path":"api/tags/归正先生.json"},{"name":"脏象正义","path":"api/tags/脏象正义.json"}]},{"title":"分享：归正先生-归正哲思---神究竟想通过《圣经》对我们说什么","slug":"分享：中医归正-归正哲思---神究竟想通过《圣经》对我们说什么","date":"2018-06-20T08:48:00.000Z","updated":"2021-06-15T03:45:27.157Z","comments":true,"path":"api/articles/分享：中医归正-归正哲思---神究竟想通过《圣经》对我们说什么.json","excerpt":null,"keywords":null,"cover":"http://wx1.sinaimg.cn/large/8bf740e1gy1fshqx69z9qj20ku0rshdt.jpg","content":null,"raw":null,"categories":[{"name":"摘","path":"api/categories/摘.json"}],"tags":[{"name":"归正先生","path":"api/tags/归正先生.json"},{"name":"修为","path":"api/tags/修为.json"}]},{"title":"分享：归正先生-如果让我再学一次中医","slug":"分享：中医归正-如果让我再学一次中医","date":"2018-06-03T23:12:00.000Z","updated":"2021-06-15T03:45:27.157Z","comments":true,"path":"api/articles/分享：中医归正-如果让我再学一次中医.json","excerpt":null,"keywords":null,"cover":"http://wx1.sinaimg.cn/large/8bf740e1gy1fryscnt8f6j20mv0cegtf.jpg","content":null,"raw":null,"categories":[{"name":"摘","path":"api/categories/摘.json"}],"tags":[{"name":"归正先生","path":"api/tags/归正先生.json"},{"name":"学医","path":"api/tags/学医.json"}]},{"title":"分享：归正先生-夏日凉茶---你所不知道的慢性自残","slug":"分享：中医归正-夏日凉茶---你所不知道的慢性自残","date":"2018-05-19T09:33:00.000Z","updated":"2021-06-15T03:45:27.157Z","comments":true,"path":"api/articles/分享：中医归正-夏日凉茶---你所不知道的慢性自残.json","excerpt":null,"keywords":null,"cover":"http://wx1.sinaimg.cn/large/8bf740e1gy1frgom7hi7ij20hs0dygtz.jpg","content":null,"raw":null,"categories":[{"name":"摘","path":"api/categories/摘.json"}],"tags":[{"name":"归正先生","path":"api/tags/归正先生.json"},{"name":"春夏养阳","path":"api/tags/春夏养阳.json"},{"name":"凉茶","path":"api/tags/凉茶.json"}]},{"title":"分享：归正先生-须弥山","slug":"分享：中医归正-须弥山","date":"2018-05-12T08:09:00.000Z","updated":"2021-06-15T03:45:27.161Z","comments":true,"path":"api/articles/分享：中医归正-须弥山.json","excerpt":null,"keywords":null,"cover":"http://wx1.sinaimg.cn/large/8bf740e1gy1fr8mni8satj20ku0atdsf.jpg","content":null,"raw":null,"categories":[{"name":"摘","path":"api/categories/摘.json"}],"tags":[{"name":"归正先生","path":"api/tags/归正先生.json"},{"name":"须弥山","path":"api/tags/须弥山.json"}]}]}